sphinxcontrib/__init__.py
sphinxcontrib/programoutput/__init__.py
sphinxcontrib/programoutput/tests/__init__.py
sphinxcontrib/programoutput/tests/test_cache.py
sphinxcontrib/programoutput/tests/test_command.py
sphinxcontrib/programoutput/tests/test_directive.py
sphinxcontrib/programoutput/tests/test_setup.py
sphinxcontrib/programoutput/tests/test_util.py
sphinxcontrib_programoutput-0.18.dist-info/LICENSE
sphinxcontrib_programoutput-0.18.dist-info/METADATA
sphinxcontrib_programoutput-0.18.dist-info/WHEEL
sphinxcontrib_programoutput-0.18.dist-info/top_level.txt
sphinxcontrib_programoutput-0.18.dist-info/RECORD
