Metadata-Version: 2.1
Name: sphinxcontrib-programoutput
Version: 0.18
Summary: Sphinx extension to include program output
Home-page: https://sphinxcontrib-programoutput.readthedocs.org/
Author: Sebastian Wiesner
Author-email: lunaryorn@gmail.com
Maintainer: Jason Madden
Maintainer-email: jason@seecoresoftware.com
License: BSD
Keywords: sphinx cli command output program example
Platform: any
Classifier: Development Status :: 5 - Production/Stable
Classifier: Intended Audience :: Developers
Classifier: License :: OSI Approved :: BSD License
Classifier: Operating System :: OS Independent
Classifier: Programming Language :: Python
Classifier: Programming Language :: Python :: 3 :: Only
Classifier: Programming Language :: Python :: 3.8
Classifier: Programming Language :: Python :: 3.9
Classifier: Programming Language :: Python :: 3.10
Classifier: Programming Language :: Python :: 3.11
Classifier: Programming Language :: Python :: 3.12
Classifier: Programming Language :: Python :: 3.13
Classifier: Programming Language :: Python :: Implementation :: CPython
Classifier: Programming Language :: Python :: Implementation :: PyPy
Classifier: Topic :: Documentation
Classifier: Topic :: Utilities
Classifier: Framework :: Sphinx
Classifier: Framework :: Sphinx :: Extension
Requires-Python: >=3.8
License-File: LICENSE
Requires-Dist: Sphinx>=5.0.0
Provides-Extra: docs
Requires-Dist: furo; extra == "docs"
Provides-Extra: test
